libpulse/__init__.py
libpulse/libpulse.py
libpulse/libpulse_ctypes.py
libpulse/mainloop.py
libpulse/pactl.py
libpulse/pulse_enums.py
libpulse/pulse_functions.py
libpulse/pulse_structs.py
libpulse/pulse_types.py
libpulse/tests/__init__.py
libpulse/tests/test_libpulse.py
libpulse/tests/test_libpulse_ctypes.py
libpulse/tests/test_pactl.py
libpulse-0.6.dist-info/entry_points.txt
libpulse-0.6.dist-info/LICENSE
libpulse-0.6.dist-info/WHEEL
libpulse-0.6.dist-info/METADATA
libpulse-0.6.dist-info/RECORD
