Metadata-Version: 2.3
Name: libpulse
Version: 0.6
Summary: Asyncio interface to the Pulseaudio and Pipewire pulse library.
Keywords: pulseaudio,pipewire,asyncio,ctypes
Author-email: Xavier de Gaye <xdegaye@gmail.com>
Requires-Python: >=3.8,<4
Classifier: Development Status :: 2 - Pre-Alpha
Classifier: Framework :: AsyncIO
Classifier: License :: OSI Approved :: MIT License
Classifier: Operating System :: Unix
Classifier: Programming Language :: Python :: 3
Classifier: Topic :: Multimedia :: Sound/Audio :: Players
Project-URL: Changelog, https://libpulse.readthedocs.io/en/stable/history.html
Project-URL: Documentation, https://libpulse.readthedocs.io/en/stable/
Project-URL: Source, https://gitlab.com/xdegaye/libpulse
